README.md
setup.py
nimbleway/__init__.py
nimbleway/ask.py
nimbleway/client.py
nimbleway/webapi.py
nimbleway.egg-info/PKG-INFO
nimbleway.egg-info/SOURCES.txt
nimbleway.egg-info/dependency_links.txt
nimbleway.egg-info/requires.txt
nimbleway.egg-info/top_level.txt